LekaiPmpPeixunJiangyi/README.md
LekaiPmpPeixunJiangyi/__init__.py
LekaiPmpPeixunJiangyi/__main__.py
LekaiPmpPeixunJiangyi/file.pdf
LekaiPmpPeixunJiangyi/index.html
lekai_pmp_peixun_jiangyi-2024.3.6.0.dist-info/METADATA
lekai_pmp_peixun_jiangyi-2024.3.6.0.dist-info/WHEEL
lekai_pmp_peixun_jiangyi-2024.3.6.0.dist-info/entry_points.txt
lekai_pmp_peixun_jiangyi-2024.3.6.0.dist-info/top_level.txt
lekai_pmp_peixun_jiangyi-2024.3.6.0.dist-info/RECORD
